unitree/__init__.py
unitree/_version.py
unitree/tests/__init__.py
unitree/tests/conftest.py
unitree/tests/test_examples.py
unitree-0.0.1.dist-info/AUTHORS.rst
unitree-0.0.1.dist-info/LICENSE
unitree-0.0.1.dist-info/METADATA
unitree-0.0.1.dist-info/WHEEL
unitree-0.0.1.dist-info/entry_points.txt
unitree-0.0.1.dist-info/top_level.txt
unitree-0.0.1.dist-info/RECORD
