Metadata-Version: 2.1
Name: unitree
Version: 0.0.1
Summary: A nice tree.
Home-page: https://github.com/appletree120th/unitree
Author: Apple Tree
Author-email: appletree120th@gmail.com
License: BSD (3-clause)
Platform: UNKNOWN
Classifier: Development Status :: 2 - Pre-Alpha
Classifier: Natural Language :: English
Classifier: Programming Language :: Python :: 3
Requires-Python: >=3.8
